common/__init__.py
common/exceptions.py
pyds/__init__.py
pyds/disjointsets/__init__.py
pyds/disjointsets/api.py
pyds/disjointsets/base.py
pyds/disjointsets/exceptions.py
pyds/graph/__init__.py
pyds/graph/api.py
pyds/graph/base.py
pyds/graph/exceptions.py
pyds/heap/__init__.py
pyds/heap/api.py
pyds/heap/base.py
pyds/heap/exceptions.py
pyds/tree/__init__.py
pyds/tree/api.py
pyds/tree/base.py
pyds/tree/decorators.py
pyds/tree/exceptions.py
pyds/tree/traversal.py
py_ds-0.2.1.dist-info/LICENCE
py_ds-0.2.1.dist-info/METADATA
py_ds-0.2.1.dist-info/WHEEL
py_ds-0.2.1.dist-info/top_level.txt
py_ds-0.2.1.dist-info/RECORD
