Metadata-Version: 2.1
Name: py-ds
Version: 0.2.1
Summary: Ready to use data structures
Home-page: https://github.com/nitinkatyal1314/data-structures
Author: Nitin Katyal
Author-email: nitinkatyal1314@gmail.com
License: MIT License
Platform: UNKNOWN
Requires-Python: >=3.6
License-File: LICENCE
